akatsuki_proto/__init__.py
akatsuki_proto/messages/__init__.py
akatsuki_proto/messages/change_username_command.py
akatsuki_proto/messages/change_username_command.pyi
akatsuki_proto/messages/change_username_completed_event.py
akatsuki_proto/messages/change_username_completed_event.pyi
akatsuki_proto/messages/change_username_fail_reason.py
akatsuki_proto/messages/change_username_fail_reason.pyi
akatsuki_proto/messages/change_username_failed_event.py
akatsuki_proto/messages/change_username_failed_event.pyi
akatsuki_proto-0.1.4.dist-info/METADATA
akatsuki_proto-0.1.4.dist-info/WHEEL
akatsuki_proto-0.1.4.dist-info/top_level.txt
akatsuki_proto-0.1.4.dist-info/RECORD
