Metadata-Version: 2.1
Name: akatsuki-proto
Version: 0.1.4
Summary: Protobuf files & source generation for Akatsuki
Home-page: UNKNOWN
Author: Akatsuki
License: UNKNOWN
Platform: UNKNOWN
Requires-Python: >=3.9
Requires-Dist: protobuf
